jellyfin_accounts/__init__.py
jellyfin_accounts/config.py
jellyfin_accounts/data/config-base.json
jellyfin_accounts/data/config-default.ini
jellyfin_accounts/data/created.html
jellyfin_accounts/data/created.txt
jellyfin_accounts/data/email.html
jellyfin_accounts/data/email.txt
jellyfin_accounts/data/expired.html
jellyfin_accounts/data/expired.txt
jellyfin_accounts/data/invite-email.html
jellyfin_accounts/data/invite-email.txt
jellyfin_accounts/data/services/jf-accounts.service
jellyfin_accounts/data/static/android-chrome-192x192.png
jellyfin_accounts/data/static/android-chrome-512x512.png
jellyfin_accounts/data/static/apple-touch-icon.png
jellyfin_accounts/data/static/browserconfig.xml
jellyfin_accounts/data/static/bs4-jf.css
jellyfin_accounts/data/static/bs4.css
jellyfin_accounts/data/static/bs5-jf.css
jellyfin_accounts/data/static/bs5.css
jellyfin_accounts/data/static/favicon-16x16.png
jellyfin_accounts/data/static/favicon-32x32.png
jellyfin_accounts/data/static/favicon.ico
jellyfin_accounts/data/static/mstile-150x150.png
jellyfin_accounts/data/static/safari-pinned-tab.svg
jellyfin_accounts/data/static/serialize.js
jellyfin_accounts/data/static/setup.js
jellyfin_accounts/data/static/site.webmanifest
jellyfin_accounts/data/templates/404.html
jellyfin_accounts/data/templates/admin.html
jellyfin_accounts/data/templates/admin.js
jellyfin_accounts/data/templates/form.html
jellyfin_accounts/data/templates/invalidCode.html
jellyfin_accounts/data/templates/setup.html
jellyfin_accounts/data_store.py
jellyfin_accounts/email.py
jellyfin_accounts/generate_ini.py
jellyfin_accounts/invite_daemon.py
jellyfin_accounts/jf_api.py
jellyfin_accounts/login.py
jellyfin_accounts/pw_reset.py
jellyfin_accounts/setup.py
jellyfin_accounts/validate_password.py
jellyfin_accounts/web.py
jellyfin_accounts/web_api.py
jellyfin_accounts-0.3.9.dist-info/entry_points.txt
jellyfin_accounts-0.3.9.dist-info/LICENSE
jellyfin_accounts-0.3.9.dist-info/WHEEL
jellyfin_accounts-0.3.9.dist-info/METADATA
jellyfin_accounts-0.3.9.dist-info/RECORD
