Metadata-Version: 2.1
Name: jellyfin-accounts
Version: 0.3.9
Summary: A simple account management system for Jellyfin
Home-page: https://github.com/hrfee/jellyfin-accounts
License: MIT
Keywords: jellyfin,jf-accounts
Author: Harvey Tindall
Author-email: harveyltindall@gmail.com
Requires-Python: >=3.6,<4.0
Classifier: License :: OSI Approved :: MIT License
Classifier: Operating System :: OS Independent
Classifier: Programming Language :: Python :: 3
Classifier: Programming Language :: Python :: 3.6
Classifier: Programming Language :: Python :: 3.7
Classifier: Programming Language :: Python :: 3.8
Requires-Dist: flask (>=1.1.2,<2.0.0)
Requires-Dist: flask-httpauth (>=3.3.0)
Requires-Dist: itsdangerous (>=1.1.0,<2.0.0)
Requires-Dist: packaging (>=20.4,<21.0)
Requires-Dist: passlib (>=1.7.2,<2.0.0)
Requires-Dist: psutil (>=5.7.2,<6.0.0)
Requires-Dist: pyopenssl (>=19.1.0,<20.0.0)
Requires-Dist: python-dateutil (>=2.8.1,<3.0.0)
Requires-Dist: pytz (>=2020.1,<2021.0)
Requires-Dist: requests (>=2.23.0,<3.0.0)
Requires-Dist: waitress (>=1.4.3,<2.0.0)
Requires-Dist: watchdog (>=0.10.2,<0.11.0)
Project-URL: Repository, https://github.com/hrfee/jellyfin-accounts
